feature_reviser/__init__.py
feature_reviser/feature_selection/reviser.py
feature_reviser/feature_selection/selector.py
feature_reviser/transformer/base_transformer.py
feature_reviser/transformer/datetime_transformer.py
feature_reviser/transformer/encoder_transformer.py
feature_reviser/transformer/generic_transformer.py
feature_reviser/transformer/number_transformer.py
feature_reviser/transformer/string_transformer.py
feature_reviser/utils.py
feature_reviser-0.3.94.dist-info/LICENSE
feature_reviser-0.3.94.dist-info/WHEEL
feature_reviser-0.3.94.dist-info/METADATA
feature_reviser-0.3.94.dist-info/RECORD
