Metadata-Version: 2.1
Name: feature-reviser
Version: 0.3.94
Summary: A collection of various scikit-learn transformers for all kinds of preprocessing and feature engineering
Home-page: https://chrislemke.github.io/feature-reviser/
License: MIT
Keywords: feature engineering,preprocessing,feature selection,scikit-learn,pipelines,pandas,machine learning,data science
Author: Christopher Lemke
Author-email: chris@syhbl.mozmail.com
Requires-Python: >=3.8,<3.11
Classifier: Intended Audience :: Science/Research
Classifier: License :: OSI Approved :: MIT License
Classifier: Programming Language :: Python :: 3
Classifier: Programming Language :: Python :: 3.8
Classifier: Programming Language :: Python :: 3.9
Classifier: Programming Language :: Python :: 3.10
Classifier: Topic :: Scientific/Engineering :: Artificial Intelligence
Classifier: Topic :: Scientific/Engineering :: Information Analysis
Requires-Dist: feature-engine (==1.4.1)
Requires-Dist: joblib (==1.2.0)
Requires-Dist: numpy (>=1.20.3,<=1.23.4)
Requires-Dist: pandas (>=1.1.3,<=1.5.0)
Requires-Dist: phonenumbers (==8.12.57)
Requires-Dist: scikit-learn (>=1.0.2,<=1.1.2)
Project-URL: Documentation, https://chrislemke.github.io/feature-reviser/
Project-URL: Repository, https://github.com/chrislemke/feature-reviser
